Workbook

Sheet Instellingen
A1: Kostenaannames
A2: Blauwe cellen pas je zelf aan op basis van de actuele tarievenkaart van je broker.
A4: Parameter | B4: Waarde | C4: Toelichting / bron
A5: Vaste transactiekosten per order (€) | B5: 5 | C5: €5 per order bij ABN AMRO buitenlandse aandelen (controleer tarievenkaart)
A6: Variabele transactiekosten (% van orderwaarde) | B6: 0.0005 | C6: 0,05% bij ABN AMRO buitenlandse aandelen
A7: Wisselkoersmarge per kant (% van orderwaarde) | B7: 0.002 | C7: Schatting voor EUR<>USD omrekening; 0 als je in EUR-aandelen handelt
A8: Servicekosten per jaar (% van portefeuille) | B8: 0.002 | C8: 0,20%/jaar volgens review; tarievenkaart is leidend
A9: Streefwinst per trade (%) | B9: 0.05 | C9: Jouw exit-doel: verkopen bij +5%
A12: Break-even: minimale koersstijging om quitte te spelen
A13: Bij een order van €1.000 betaal je 2x transactiekosten (koop + verkoop) plus marge. Dat is grofweg (2 × €5) + (2 × 0,05% × €1.000) = €11. Je moet dus ~1,1% stijgen voordat je winst maakt — en dat percentage is groter naarmate je order kleiner is.

Sheet Trades
A1: Transactielogboek
A2: Witte kolommen vul je in. Grijze (formules) rekenen automatisch het netto rendement uit na alle kosten.
A4: Ticker | B4: Naam | C4: Koopdatum | D4: Koop­koers (€) | E4: Aantal | F4: Orderwaarde koop (€) | G4: Koopkosten (€) | H4: Verkoop­datum | I4: Verkoop­koers (€) | J4: Orderwaarde verkoop (€) | K4: Verkoopkosten (€) | L4: Bruto W/V (€) | M4: Totale kosten (€) | N4: Netto W/V (€) | O4: Netto rendement % | P4: Status
A5: ASML | B5: ASML Holding | C5: 2026-06-10 | D5: 980 | E5: 5 | F5: =D5*E5 | G5: =Instellingen!$B$5+(Instellingen!$B$6+Instellingen!$B$7)*F5 | H5: 2026-06-24 | I5: 1031 | J5: =IF(I5="","",I5*E5) | K5: =IF(I5="","",Instellingen!$B$5+(Instellingen!$B$6+Instellingen!$B$7)*J5) | L5: =IF(I5="","",J5-F5) | M5: =IF(I5="",G5,G5+K5) | N5: =IF(I5="","",L5-M5) | O5: =IF(I5="","",N5/F5) | P5: =IF(I5="","Open",IF(N5>=0,"Winst","Verlies"))
A6: NVDA | B6: NVIDIA | C6: 2026-06-12 | D6: 118.5 | E6: 40 | F6: =D6*E6 | G6: =Instellingen!$B$5+(Instellingen!$B$6+Instellingen!$B$7)*F6 | J6: =IF(I6="","",I6*E6) | K6: =IF(I6="","",Instellingen!$B$5+(Instellingen!$B$6+Instellingen!$B$7)*J6) | L6: =IF(I6="","",J6-F6) | M6: =IF(I6="",G6,G6+K6) | N6: =IF(I6="","",L6-M6) | O6: =IF(I6="","",N6/F6) | P6: =IF(I6="","Open",IF(N6>=0,"Winst","Verlies"))
A7: SHELL | B7: Shell plc | C7: 2026-06-15 | D7: 31.2 | E7: 60 | F7: =D7*E7 | G7: =Instellingen!$B$5+(Instellingen!$B$6+Instellingen!$B$7)*F7 | H7: 2026-06-27 | I7: 32.05 | J7: =IF(I7="","",I7*E7) | K7: =IF(I7="","",Instellingen!$B$5+(Instellingen!$B$6+Instellingen!$B$7)*J7) | L7: =IF(I7="","",J7-F7) | M7: =IF(I7="",G7,G7+K7) | N7: =IF(I7="","",L7-M7) | O7: =IF(I7="","",N7/F7) | P7: =IF(I7="","Open",IF(N7>=0,"Winst","Verlies"))
F8: =IF(E8="","",D8*E8) | G8: =IF(F8="","",Instellingen!$B$5+(Instellingen!$B$6+Instellingen!$B$7)*F8) | J8: =IF(I8="","",I8*E8) | K8: =IF(I8="","",Instellingen!$B$5+(Instellingen!$B$6+Instellingen!$B$7)*J8) | L8: =IF(I8="","",J8-F8) | M8: =IF(F8="","",IF(I8="",G8,G8+K8)) | N8: =IF(I8="","",L8-M8) | O8: =IF(I8="","",N8/F8) | P8: =IF(D8="","",IF(I8="","Open",IF(N8>=0,"Winst","Verlies")))
F9: =IF(E9="","",D9*E9) | G9: =IF(F9="","",Instellingen!$B$5+(Instellingen!$B$6+Instellingen!$B$7)*F9) | J9: =IF(I9="","",I9*E9) | K9: =IF(I9="","",Instellingen!$B$5+(Instellingen!$B$6+Instellingen!$B$7)*J9) | L9: =IF(I9="","",J9-F9) | M9: =IF(F9="","",IF(I9="",G9,G9+K9)) | N9: =IF(I9="","",L9-M9) | O9: =IF(I9="","",N9/F9) | P9: =IF(D9="","",IF(I9="","Open",IF(N9>=0,"Winst","Verlies")))
F10: =IF(E10="","",D10*E10) | G10: =IF(F10="","",Instellingen!$B$5+(Instellingen!$B$6+Instellingen!$B$7)*F10) | J10: =IF(I10="","",I10*E10) | K10: =IF(I10="","",Instellingen!$B$5+(Instellingen!$B$6+Instellingen!$B$7)*J10) | L10: =IF(I10="","",J10-F10) | M10: =IF(F10="","",IF(I10="",G10,G10+K10)) | N10: =IF(I10="","",L10-M10) | O10: =IF(I10="","",N10/F10) | P10: =IF(D10="","",IF(I10="","Open",IF(N10>=0,"Winst","Verlies")))
F11: =IF(E11="","",D11*E11) | G11: =IF(F11="","",Instellingen!$B$5+(Instellingen!$B$6+Instellingen!$B$7)*F11) | J11: =IF(I11="","",I11*E11) | K11: =IF(I11="","",Instellingen!$B$5+(Instellingen!$B$6+Instellingen!$B$7)*J11) | L11: =IF(I11="","",J11-F11) | M11: =IF(F11="","",IF(I11="",G11,G11+K11)) | N11: =IF(I11="","",L11-M11) | O11: =IF(I11="","",N11/F11) | P11: =IF(D11="","",IF(I11="","Open",IF(N11>=0,"Winst","Verlies")))
F12: =IF(E12="","",D12*E12) | G12: =IF(F12="","",Instellingen!$B$5+(Instellingen!$B$6+Instellingen!$B$7)*F12) | J12: =IF(I12="","",I12*E12) | K12: =IF(I12="","",Instellingen!$B$5+(Instellingen!$B$6+Instellingen!$B$7)*J12) | L12: =IF(I12="","",J12-F12) | M12: =IF(F12="","",IF(I12="",G12,G12+K12)) | N12: =IF(I12="","",L12-M12) | O12: =IF(I12="","",N12/F12) | P12: =IF(D12="","",IF(I12="","Open",IF(N12>=0,"Winst","Verlies")))
F13: =IF(E13="","",D13*E13) | G13: =IF(F13="","",Instellingen!$B$5+(Instellingen!$B$6+Instellingen!$B$7)*F13) | J13: =IF(I13="","",I13*E13) | K13: =IF(I13="","",Instellingen!$B$5+(Instellingen!$B$6+Instellingen!$B$7)*J13) | L13: =IF(I13="","",J13-F13) | M13: =IF(F13="","",IF(I13="",G13,G13+K13)) | N13: =IF(I13="","",L13-M13) | O13: =IF(I13="","",N13/F13) | P13: =IF(D13="","",IF(I13="","Open",IF(N13>=0,"Winst","Verlies")))
F14: =IF(E14="","",D14*E14) | G14: =IF(F14="","",Instellingen!$B$5+(Instellingen!$B$6+Instellingen!$B$7)*F14) | J14: =IF(I14="","",I14*E14) | K14: =IF(I14="","",Instellingen!$B$5+(Instellingen!$B$6+Instellingen!$B$7)*J14) | L14: =IF(I14="","",J14-F14) | M14: =IF(F14="","",IF(I14="",G14,G14+K14)) | N14: =IF(I14="","",L14-M14) | O14: =IF(I14="","",N14/F14) | P14: =IF(D14="","",IF(I14="","Open",IF(N14>=0,"Winst","Verlies")))
F15: =IF(E15="","",D15*E15) | G15: =IF(F15="","",Instellingen!$B$5+(Instellingen!$B$6+Instellingen!$B$7)*F15) | J15: =IF(I15="","",I15*E15) | K15: =IF(I15="","",Instellingen!$B$5+(Instellingen!$B$6+Instellingen!$B$7)*J15) | L15: =IF(I15="","",J15-F15) | M15: =IF(F15="","",IF(I15="",G15,G15+K15)) | N15: =IF(I15="","",L15-M15) | O15: =IF(I15="","",N15/F15) | P15: =IF(D15="","",IF(I15="","Open",IF(N15>=0,"Winst","Verlies")))
F16: =IF(E16="","",D16*E16) | G16: =IF(F16="","",Instellingen!$B$5+(Instellingen!$B$6+Instellingen!$B$7)*F16) | J16: =IF(I16="","",I16*E16) | K16: =IF(I16="","",Instellingen!$B$5+(Instellingen!$B$6+Instellingen!$B$7)*J16) | L16: =IF(I16="","",J16-F16) | M16: =IF(F16="","",IF(I16="",G16,G16+K16)) | N16: =IF(I16="","",L16-M16) | O16: =IF(I16="","",N16/F16) | P16: =IF(D16="","",IF(I16="","Open",IF(N16>=0,"Winst","Verlies")))
F17: =IF(E17="","",D17*E17) | G17: =IF(F17="","",Instellingen!$B$5+(Instellingen!$B$6+Instellingen!$B$7)*F17) | J17: =IF(I17="","",I17*E17) | K17: =IF(I17="","",Instellingen!$B$5+(Instellingen!$B$6+Instellingen!$B$7)*J17) | L17: =IF(I17="","",J17-F17) | M17: =IF(F17="","",IF(I17="",G17,G17+K17)) | N17: =IF(I17="","",L17-M17) | O17: =IF(I17="","",N17/F17) | P17: =IF(D17="","",IF(I17="","Open",IF(N17>=0,"Winst","Verlies")))
F18: =IF(E18="","",D18*E18) | G18: =IF(F18="","",Instellingen!$B$5+(Instellingen!$B$6+Instellingen!$B$7)*F18) | J18: =IF(I18="","",I18*E18) | K18: =IF(I18="","",Instellingen!$B$5+(Instellingen!$B$6+Instellingen!$B$7)*J18) | L18: =IF(I18="","",J18-F18) | M18: =IF(F18="","",IF(I18="",G18,G18+K18)) | N18: =IF(I18="","",L18-M18) | O18: =IF(I18="","",N18/F18) | P18: =IF(D18="","",IF(I18="","Open",IF(N18>=0,"Winst","Verlies")))
F19: =IF(E19="","",D19*E19) | G19: =IF(F19="","",Instellingen!$B$5+(Instellingen!$B$6+Instellingen!$B$7)*F19) | J19: =IF(I19="","",I19*E19) | K19: =IF(I19="","",Instellingen!$B$5+(Instellingen!$B$6+Instellingen!$B$7)*J19) | L19: =IF(I19="","",J19-F19) | M19: =IF(F19="","",IF(I19="",G19,G19+K19)) | N19: =IF(I19="","",L19-M19) | O19: =IF(I19="","",N19/F19) | P19: =IF(D19="","",IF(I19="","Open",IF(N19>=0,"Winst","Verlies")))
... F22: =IF(E22="","",D22*E22) | G22: =IF(F22="","",Instellingen!$B$5+(Instellingen!$B$6+Instellingen!$B$7)*F22) | J22: =IF(I22="","",I22*E22) | K22: =IF(I22="","",Instellingen!$B$5+(Instellingen!$B$6+Instellingen!$B$7)*J22) | L22: =IF(I22="","",J22-F22) | M22: =IF(F22="","",IF(I22="",G22,G22+K22)) | N22: =IF(I22="","",L22-M22) | O22: =IF(I22="","",N22/F22) | P22: =IF(D22="","",IF(I22="","Open",IF(N22>=0,"Winst","Verlies")))
A24: TOTAAL | L24: =SUM(L5:L22) | M24: =SUM(M5:M22) | N24: =SUM(N5:N22)
A25: Win-rate | B25: =COUNTIF(P5:P22,"Winst")&" winst / "&COUNTIF(P5:P22,"Verlies")&" verlies"

Sheet Screener
A1: Dagelijkse screener — consistente stijgers (alle periodes)
A2: Kandidaten die over alle periodes tegelijk stijgen. Voorbeelddata; vervang met echte API-output.
A4: Datum gevonden | B4: Ticker | C4: Naam | D4: Koers (€) | E4: % 1 dag | F4: % 1 week | G4: % 1 mnd | H4: % 6 mnd | I4: % 1 jaar | J4: Voldoet aan filter | K4: Nieuwslink
A5: 2026-06-30 | B5: NVDA | C5: NVIDIA | D5: 118.5 | E5: 0.062 | F5: 0.081 | G5: 0.143 | H5: 0.31 | I5: 0.62 | J5: =IF(AND(E5>=0,F5>=0,G5>=0,H5>=0,I5>=0),"JA","nee") | K5: https://finnhub.io/
A6: 2026-06-30 | B6: ASML | C6: ASML Holding | D6: 1031 | E6: 0.051 | F6: 0.066 | G6: 0.092 | H6: 0.18 | I6: 0.27 | J6: =IF(AND(E6>=0,F6>=0,G6>=0,H6>=0,I6>=0),"JA","nee") | K6: https://finnhub.io/
A7: 2026-06-30 | B7: NOVO | C7: Novo Nordisk | D7: 92.4 | E7: 0.058 | F7: 0.072 | G7: 0.11 | H7: 0.04 | I7: -0.12 | J7: =IF(AND(E7>=0,F7>=0,G7>=0,H7>=0,I7>=0),"JA","nee") | K7: https://finnhub.io/
A8: 2026-06-30 | B8: SHELL | C8: Shell plc | D8: 32.05 | E8: 0.027 | F8: 0.041 | G8: 0.06 | H8: 0.09 | I8: 0.14 | J8: =IF(AND(E8>=0,F8>=0,G8>=0,H8>=0,I8>=0),"JA","nee") | K8: https://finnhub.io/
A9: 2026-06-30 | B9: ADYEN | C9: Adyen | D9: 1450 | E9: 0.071 | F9: 0.12 | G9: 0.19 | H9: 0.22 | I9: 0.41 | J9: =IF(AND(E9>=0,F9>=0,G9>=0,H9>=0,I9>=0),"JA","nee") | K9: https://finnhub.io/
A10: 2026-07-02 | B10: MRNA | C10: MRNA | D10: 72.5 | E10: 0.035270616 | F10: 0.19993383 | G10: 0.57403382 | H10: 1.3840842 | I10: 1.5270128 | J10: JA | K10: https://finnhub.io/api/news?id=ce17c9b20616cb8ef7fb4c956cf8e01b2a5840726dcd42cb21f3b2815fa23a4d
A11: 2026-07-02 | B11: PANW | C11: PANW | D11: 352.04001 | E11: 0.032314879 | F11: 0.23410221 | G11: 0.1715921 | H11: 0.88407812 | I11: 0.78175931 | J11: JA | K11: https://finnhub.io/api/news?id=ce17c9b20616cb8ef7fb4c956cf8e01b2a5840726dcd42cb21f3b2815fa23a4d
A12: 2026-07-02 | B12: VLO | C12: VLO | D12: 269.44 | E12: 0.034556903 | F12: 0.11141365 | G12: 0.067004585 | H12: 0.65216463 | I12: 1.0022744 | J12: JA | K12: https://finnhub.io/api/news?id=d71c87b4e3ae6fb243d4d6b47bfde62364599267d973b748c45a11855a68bd8d
A13: 2026-07-02 | B13: FTNT | C13: FTNT | D13: 158.98 | E13: 0.034891295 | F13: 0.094300641 | G13: 0.080467557 | H13: 0.97957914 | I13: 0.5520843 | J13: JA | K13: https://finnhub.io/api/news?id=3f2de5e2e03c7894f32a29aa93cebaad071cf8a927d60b440dfc30acd56f0e67
A14: 2026-07-02 | B14: ILMN | C14: ILMN | D14: 183.89 | E14: 0.045839717 | F14: 0.050259885 | G14: 0.11855235 | H14: 0.3852354 | I14: 0.87356084 | J14: JA | K14: https://finnhub.io/api/news?id=642dbaaa4dcdeb2324e5772ee4e261f7b01f70bc105a3db58ad95119f9c5dc79
A15: 2026-07-02 | B15: MPC | C15: MPC | D15: 264.87 | E15: 0.035983874 | F15: 0.074479741 | G15: 0.024008317 | H15: 0.63113984 | I15: 0.58901902 | J15: JA | K15: https://finnhub.io/api/news?id=9932bacd993c61d07cb86adcffc985bc1b5144f8e2f858a919eb685252fd5fb2
A16: 2026-07-02 | B16: OKTA | C16: OKTA | D16: 140.46001 | E16: 0.029388126 | F16: 0.18451682 | G16: 0.0047929999 | H16: 0.60654245 | I16: 0.42526639 | J16: JA | K16: https://finnhub.io/api/news?id=d9aae01b2aabcf5b23e2d9d799fc7073679e40d2e97dce70573f9a3040237524
A17: 2026-07-02 | B17: IBKR | C17: IBKR | D17: 93.25 | E17: 0.071346496 | F17: 0.0049574208 | G17: 0.051415012 | H17: 0.43761086 | I17: 0.66333803 | J17: JA | K17: https://finnhub.io/api/news?id=bcdeb32a91bc322e8f9d5505faecf809567ee18e2ab59d25261d806bc83e9fd2
A18: 2026-07-02 | B18: JNJ | C18: JNJ | D18: 253.98 | E18: 3.93531e-05 | F18: 0.053858903 | G18: 0.13632501 | H18: 0.24111261 | I18: 0.66961235 | J18: JA | K18: https://finnhub.io/api/news?id=c8e6dc50fd735c40b044c5e600be9279c4aaf39d3d94ab56517405101f9a9193
A19: 2026-07-02 | B19: WELL | C19: WELL | D19: 230.19 | E19: 0.014186902 | F19: 0.039561081 | G19: 0.16634577 | H19: 0.23295418 | I19: 0.54175343 | J19: JA | K19: https://finnhub.io/api/news?id=5fcd1dac75c2dc37080b1e974e293954b5b64bbbd74a3fc8f7eb9a5107a0396c
A20: 2026-07-02 | B20: MNST | C20: MNST | D20: 97.349998 | E20: 0.01279646 | F20: 0.027983122 | G20: 0.092592594 | H20: 0.25758938 | I20: 0.53210571 | J20: JA | K20: https://finnhub.io/api/news?id=72bf0ae826fe1cfbddf3f651ac1489245c4b00cc230f67a8d212075c3981c87a
A21: 2026-07-02 | B21: GE | C21: GE | D21: 374.94 | E21: 0.0032376085 | F21: 0.02476221 | G21: 0.15508317 | H21: 0.20429188 | I21: 0.51363158 | J21: JA | K21: https://finnhub.io/api/news?id=9fd240f15dd54783c692edf77484e4ff7fe4d876119ffc8c9460fb331faf3242
... A35: 2026-07-02 | B35: BAC | C35: BAC | D35: 58.360001 | E35: 0.024219043 | F35: 0.010912889 | G35: 0.13887066 | H35: 0.067200749 | I35: 0.2384483 | J35: JA | K35: https://finnhub.io/api/news?id=62e3320c8067d97fedf1de31317e2f7b7b8031e8a7b5e659cc418c7a4ff72c37
A36: 2026-07-02 | B36: LNG | C36: LNG | D36: 243.92 | E36: 0.020543089 | F36: 0.056571071 | G36: 0.070387892 | H36: 0.26722134 | I36: 0.043511692 | J36: JA
A37: 2026-07-02 | B37: PPG | C37: PPG | D37: 122.61 | E37: 0.010883005 | F37: 0.013473278 | G37: 0.094048371 | H37: 0.19713199 | I37: 0.081321755 | J37: JA | K37: https://finnhub.io/api/news?id=c951416ecc72a63cf30913b711c7a74304ee924ab29fcd42534cddc3814d3c39
A38: 2026-07-02 | B38: KO | C38: KO | D38: 81.290001 | E38: 0.00024614585 | F38: 0.0085608245 | G38: 0.040371704 | H38: 0.17564416 | I38: 0.16634848 | J38: JA | K38: https://finnhub.io/api/news?id=0dfc077852178496493e49b2401e7cc441fe47acd9b877d769b1356964c1bf60
A39: 2026-07-02 | B39: VRTX | C39: VRTX | D39: 498.01001 | E39: 0.0025768501 | F39: 0.048000835 | G39: 0.13597175 | H39: 0.097566934 | I39: 0.10140217 | J39: JA | K39: https://finnhub.io/api/news?id=52c78d706a9db26b953f778e31d58f1170246e7fa12bbe322dba66842da12231
A40: 2026-07-02 | B40: HEI | C40: HEI | D40: 359.70001 | E40: 0.010223037 | F40: 0.073162404 | G40: 0.079763916 | H40: 0.096577408 | I40: 0.11959973 | J40: JA | K40: https://finnhub.io/api/news?id=e19016de81486c66ffbabac7244a3c73617723904a2ab812e24b09546025899a
A41: 2026-07-02 | B41: JPM | C41: JPM | D41: 334.07001 | E41: 0.020590905 | F41: 0.0018593345 | G41: 0.12640779 | H41: 0.042898698 | I41: 0.17271103 | J41: JA | K41: https://finnhub.io/api/news?id=7845abcae42c6d8fdfb9581305ffd98552815efee432a7c5fb485089c18ab63b
A42: 2026-07-02 | B42: MET | C42: MET | D42: 87.199997 | E42: 0.030610995 | F42: 0.030732843 | G42: 0.065493657 | H42: 0.1092739 | I42: 0.10764365 | J42: JA | K42: https://finnhub.io/api/news?id=fad08d789d41b53a996fc9b4a509a59f0a955b30d7e433a39d22f2e2f310a179
A43: 2026-07-02 | B43: ED | C43: ED | D43: 110.95 | E43: 0.0028925219 | F43: 0.0020772735 | G43: 0.070945932 | H43: 0.12882465 | I43: 0.13749892 | J43: JA | K43: https://finnhub.io/api/news?id=c0cb7fff76359340c3cc313f962cb8d84dd1acab807b53770a183e3dcea94758
A44: 2026-07-02 | B44: YUM | C44: YUM | D44: 161.59 | E44: 0.010821942 | F44: 0.056005697 | G44: 0.095451172 | H44: 0.071948663 | I44: 0.095280318 | J44: JA | K44: https://finnhub.io/api/news?id=f8834127da5c310f76a0aea9d94163537ed905040f1b8a9bda7db45f375c1408
A45: 2026-07-02 | B45: LMT | C45: LMT | D45: 521.82001 | E45: 0.024261014 | F45: 0.061386364 | G45: 0.010300111 | H45: 0.081975796 | I45: 0.15013575 | J45: JA | K45: https://finnhub.io/api/news?id=398a6a71dc65a98b2e5e177bcbc62385eda75be538c33794adc9f6047bf96cda
A46: 2026-07-02 | B46: EA | C46: EA | D46: 205.45 | E46: 0.0019996278 | F46: 0.0045471966 | G46: 0.017079193 | H46: 0.0072856375 | I46: 0.29673706 | J46: JA | K46: https://finnhub.io/api/news?id=8f0208ea829fe2fcb50b52be94c337c6972843f388e3e41d7408dd7761552679
A47: 2026-07-02 | B47: UPS | C47: UPS | D47: 109.54 | E47: 0.018976753 | F47: 0.032033178 | G47: 0.0047698064 | H47: 0.13347894 | I47: 0.1206391 | J47: JA | K47: https://finnhub.io/api/news?id=8ca4c5c5e5f0ff12b9561c7fc957213d4e1f2c6a7b67680b72554cd658e242e6
A48: 2026-07-02 | B48: AFL | C48: AFL | D48: 118.49 | E48: 0.010575675 | F48: 0.0062844829 | G48: 0.056908369 | H48: 0.080653205 | I48: 0.14405074 | J48: JA | K48: https://finnhub.io/api/news?id=50eee2404279e4791e7827e06516f6fd1e5595c94ef8851a023fc0270413f207
... A78: 2026-07-02 | B78: BAC | C78: BAC | D78: 58.360001 | E78: 0.024219043 | F78: 0.010912889 | G78: 0.13887066 | H78: 0.067200749 | I78: 0.2384482 | J78: JA | K78: https://finnhub.io/api/news?id=ec8d9cbe2d5c3e5aebba8bfad5feed0311dcb23512d5bb4f91e41953ed344d93
A79: 2026-07-02 | B79: LNG | C79: LNG | D79: 243.92 | E79: 0.020543089 | F79: 0.056571071 | G79: 0.070387892 | H79: 0.26722134 | I79: 0.043511692 | J79: JA
A80: 2026-07-02 | B80: PPG | C80: PPG | D80: 122.61 | E80: 0.010883005 | F80: 0.013473278 | G80: 0.094048371 | H80: 0.19713199 | I80: 0.081321827 | J80: JA | K80: https://finnhub.io/api/news?id=c951416ecc72a63cf30913b711c7a74304ee924ab29fcd42534cddc3814d3c39
A81: 2026-07-02 | B81: KO | C81: KO | D81: 81.290001 | E81: 0.00024614585 | F81: 0.0085608245 | G81: 0.040371704 | H81: 0.17564429 | I81: 0.16634861 | J81: JA | K81: https://finnhub.io/api/news?id=4dfb99c2729f8a478c339938646829df6d4a3a90d9c44a7de157031b571ec336
A82: 2026-07-02 | B82: VRTX | C82: VRTX | D82: 498.01001 | E82: 0.0025768501 | F82: 0.048000835 | G82: 0.13597175 | H82: 0.097566934 | I82: 0.10140217 | J82: JA | K82: https://finnhub.io/api/news?id=52c78d706a9db26b953f778e31d58f1170246e7fa12bbe322dba66842da12231
A83: 2026-07-02 | B83: HEI | C83: HEI | D83: 359.70001 | E83: 0.010223037 | F83: 0.073162404 | G83: 0.079763916 | H83: 0.096577408 | I83: 0.11959973 | J83: JA | K83: https://finnhub.io/api/news?id=e19016de81486c66ffbabac7244a3c73617723904a2ab812e24b09546025899a
A84: 2026-07-02 | B84: JPM | C84: JPM | D84: 334.07001 | E84: 0.020590905 | F84: 0.0018593345 | G84: 0.12640779 | H84: 0.042898698 | I84: 0.17271103 | J84: JA | K84: https://finnhub.io/api/news?id=f7abf78d9bb4a3ea8caa0cf2fe753f3aa1e9f16d73f973bdd9ee8d2fc99ab999
A85: 2026-07-02 | B85: MET | C85: MET | D85: 87.199997 | E85: 0.030610995 | F85: 0.030732843 | G85: 0.065493657 | H85: 0.1092738 | I85: 0.10764365 | J85: JA | K85: https://finnhub.io/api/news?id=16ab74bd9dd4b380a93e7a2b01f2f76cae33e2cf4e26b6064922093baf88ad61
A86: 2026-07-02 | B86: ED | C86: ED | D86: 110.95 | E86: 0.0028925219 | F86: 0.0020772735 | G86: 0.070945932 | H86: 0.12882465 | I86: 0.13749883 | J86: JA | K86: https://finnhub.io/api/news?id=c0cb7fff76359340c3cc313f962cb8d84dd1acab807b53770a183e3dcea94758
A87: 2026-07-02 | B87: YUM | C87: YUM | D87: 161.59 | E87: 0.010821942 | F87: 0.056005697 | G87: 0.095451172 | H87: 0.071948771 | I87: 0.095280205 | J87: JA | K87: https://finnhub.io/api/news?id=f8834127da5c310f76a0aea9d94163537ed905040f1b8a9bda7db45f375c1408
A88: 2026-07-02 | B88: LMT | C88: LMT | D88: 521.82001 | E88: 0.024261014 | F88: 0.061386364 | G88: 0.010300111 | H88: 0.081975796 | I88: 0.15013575 | J88: JA | K88: https://finnhub.io/api/news?id=5f21defb644c0e59e974bd6d1ff2f51aee8cdf449744441a6b517d99dae58313
A89: 2026-07-02 | B89: EA | C89: EA | D89: 205.45 | E89: 0.0019996278 | F89: 0.0045471966 | G89: 0.017079193 | H89: 0.0072856375 | I89: 0.29673693 | J89: JA | K89: https://finnhub.io/api/news?id=8f0208ea829fe2fcb50b52be94c337c6972843f388e3e41d7408dd7761552679
A90: 2026-07-02 | B90: UPS | C90: UPS | D90: 109.54 | E90: 0.018976753 | F90: 0.032033178 | G90: 0.0047698064 | H90: 0.13347903 | I90: 0.12063901 | J90: JA | K90: https://finnhub.io/api/news?id=8ca4c5c5e5f0ff12b9561c7fc957213d4e1f2c6a7b67680b72554cd658e242e6
A91: 2026-07-02 | B91: AFL | C91: AFL | D91: 118.49 | E91: 0.010575675 | F91: 0.0062844829 | G91: 0.056908369 | H91: 0.080653205 | I91: 0.14405065 | J91: JA | K91: https://finnhub.io/api/news?id=27d3c5c4e0fa2eb2a66aa82af873204776cb539580a8f4f663817cbb63a46de0
... A108: 2026-07-03 | B108: ABBV | C108: ABBV | D108: 261.07001 | E108: 0.039870986 | F108: 0.073743555 | G108: 0.21202421 | H108: 0.16133665 | I108: 0.41323807 | J108: JA | K108: https://finnhub.io/api/news?id=840d41f2aa0e747f2602ed1773f4dbb206a469c2fa2c4c15ce0627a85dc8e190
A109: 2026-07-03 | B109: ALL | C109: ALL | D109: 250.33 | E109: 0.029656165 | F109: 0.080872173 | G109: 0.18944215 | H109: 0.21509536 | I109: 0.31166736 | J109: JA
A110: 2026-07-03 | B110: TRV | C110: TRV | D110: 342.31 | E110: 0.0229813 | F110: 0.075465734 | G110: 0.17776022 | H110: 0.18938399 | I110: 0.35134824 | J110: JA | K110: https://finnhub.io/api/news?id=c695286d7754a1888990f708cd63bc406a376127bc2185825e118715ea2c95c2
A111: 2026-07-03 | B111: SPG | C111: SPG | D111: 226.06 | E111: 0.013721962 | F111: 0.002527793 | G111: 0.12288139 | H111: 0.24886593 | I111: 0.42794446 | J111: JA | K111: https://finnhub.io/api/news?id=b5806f77f31e2b4ba24662daf64bfdf2c4f4068f757b4ed68c067aaee848a0c0
A112: 2026-07-03 | B112: RTX | C112: RTX | D112: 199.25 | E112: 0.038950888 | F112: 0.067849316 | G112: 0.14340644 | H112: 0.094572089 | I112: 0.40067474 | J112: JA | K112: https://finnhub.io/api/news?id=840d41f2aa0e747f2602ed1773f4dbb206a469c2fa2c4c15ce0627a85dc8e190
A113: 2026-07-03 | B113: CB | C113: CB | D113: 361.17001 | E113: 0.026838774 | F113: 0.091741749 | G113: 0.16020403 | H113: 0.16418816 | I113: 0.29736655 | J113: JA | K113: https://finnhub.io/api/news?id=bb323ee154776890b99a957acd889bc35688ed89de68471ee6059f17f5ac76f5
A114: 2026-07-03 | B114: AEP | C114: AEP | D114: 138.50999 | E114: 0.025620077 | F114: 0.011021858 | G114: 0.08968605 | H114: 0.21948698 | I114: 0.38384989 | J114: JA | K114: https://finnhub.io/api/news?id=1952e01903f0e9d3aec647d9ef4dab6a424a1502268428042e941e459b4cd5dc
A115: 2026-07-03 | B115: VRTX | C115: VRTX | D115: 528.03998 | E115: 0.060299929 | F115: 0.099670928 | G115: 0.24218397 | H115: 0.16472559 | I115: 0.15537269 | J115: JA | K115: https://finnhub.io/api/news?id=326cbb0a582da9491c50a786271e36ae869915ccb646b59899c45d78f7507188
A116: 2026-07-03 | B116: APD | C116: APD | D116: 314.19 | E116: 0.02542431 | F116: 0.12936014 | G116: 0.13194796 | H116: 0.29724712 | I116: 0.1111374 | J116: JA | K116: https://finnhub.io/api/news?id=7d48082034dcd61f9df177502e82678bc76887a3a345bb490476a1d22c318f45
A117: 2026-07-03 | B117: AMGN | C117: AMGN | D117: 374.14999 | E117: 0.035480054 | F117: 0.060455717 | G117: 0.13979767 | H117: 0.15971869 | I117: 0.29828572 | J117: JA | K117: https://finnhub.io/api/news?id=03dd84a049fa940ed811f34542ecc83d6d561022c912915f3b233b5947039ce0
A118: 2026-07-03 | B118: AFRM | C118: AFRM | D118: 84.580002 | E118: 0.0087060629 | F118: 0.1005856 | G118: 0.19109984 | H118: 0.13636976 | I118: 0.23709227 | J118: JA | K118: https://finnhub.io/api/news?id=b444279dcc65ac2f7847744cfd40df9a6621b231552c36e24ed2d35c0aee532e
A119: 2026-07-03 | B119: GD | C119: GD | D119: 373.54001 | E119: 0.033963573 | F119: 0.088436253 | G119: 0.11129412 | H119: 0.12418005 | I119: 0.2999449 | J119: JA | K119: https://finnhub.io/api/news?id=b0854ad208e1cbbe4eb1a569a167ea6ab7906cb22398fe1852c09f5fd5043f8d
A120: 2026-07-03 | B120: LIN | C120: LIN | D120: 546.64001 | E120: 0.024533834 | F120: 0.046641617 | G120: 0.10578251 | H120: 0.29039271 | I120: 0.16100818 | J120: JA | K120: https://finnhub.io/api/news?id=4a7d823322e3f3eb4b85b3bfa40d6bcf14375f894fd37782cf3760da3269cb77
A121: 2026-07-03 | B121: PSA | C121: PSA | D121: 329.64001 | E121: 0.020430925 | F121: 0.027748409 | G121: 0.11219575 | H121: 0.29514019 | I121: 0.15556885 | J121: JA | K121: https://finnhub.io/api/news?id=0de81c8fee998d182650ed81721f3f37b3f96cf5cdcd4ca5301d9a38df828e40
... A145: 2026-07-03 | B145: AFL | C145: AFL | D145: 120.88 | E145: 0.020170474 | F145: 0.022413887 | G145: 0.063803575 | H145: 0.10774937 | I145: 0.1926069 | J145: JA | K145: https://finnhub.io/api/news?id=bdbe26a262d9b46a45a1993ce2f31dff42dbc6ae833be5a6c37b66e46cdbfa2a
A146: 2026-07-03 | B146: LNG | C146: LNG | D146: 245.97 | E146: 0.0084044075 | F146: 0.046235622 | G146: 0.042201631 | H146: 0.27162648 | I146: 0.033756086 | J146: JA
A147: 2026-07-03 | B147: BDX | C147: BDX | D147: 158.08 | E147: 0.033878405 | F147: 0.044259458 | G147: 0.10222562 | H147: 0.050077581 | I147: 0.16213338 | J147: JA | K147: https://finnhub.io/api/news?id=8831e57c447685f7d89edb07b4c239f2b6fa697dd0711d22279e85d63efc7d36
A148: 2026-07-03 | B148: DUK | C148: DUK | D148: 129.60001 | E148: 0.030452489 | F148: 0.019589375 | G148: 0.070278388 | H148: 0.12476112 | I148: 0.14581207 | J148: JA | K148: https://finnhub.io/api/news?id=00399df1571a1b2b1fb6fdd03303b1612067ca474c03fff0412aefb68239bf28
A149: 2026-07-03 | B149: SO | C149: SO | D149: 97.980003 | E149: 0.030067289 | F149: 0.02158273 | G149: 0.082532328 | H149: 0.14182615 | I149: 0.11006364 | J149: JA | K149: https://finnhub.io/api/news?id=d0505c14434343fe9f245676975cf1bfcacc7793d877db5483453a7a460cbce0
A150: 2026-07-03 | B150: TXRH | C150: TXRH | D150: 194.28 | E150: 0.014622953 | F150: 0.019253964 | G150: 0.13653911 | H150: 0.18055828 | I150: 0.033505748 | J150: JA | K150: https://finnhub.io/api/news?id=42c00728c27b6312e9e77b59c2acf6e10c1a2245491144b5701f8c73fef43695
A151: 2026-07-03 | B151: EQR | C151: EQR | D151: 69.830002 | E151: 0.017485132 | F151: 0.05039999 | G151: 0.065630138 | H151: 0.14536145 | I151: 0.09464158 | J151: JA | K151: https://finnhub.io/api/news?id=dc60353307f51002d4e842cdf9239b4b6cc2aa8df7a1d7d992deb8bc980cd02e
A152: 2026-07-03 | B152: ABNB | C152: ABNB | D152: 148.92999 | E152: 0.010997184 | F152: 0.049689791 | G152: 0.10852241 | H152: 0.09733268 | I152: 0.10000734 | J152: JA | K152: https://finnhub.io/api/news?id=db6bbbbecd51bc725a8042099592ee76c09758b6d69a91ab7e039ecdc2b79d92
A153: 2026-07-03 | B153: SHW | C153: SHW | D153: 352.48001 | E153: 0.018581198 | F153: 0.039518771 | G153: 0.20300345 | H153: 0.093032642 | I153: 0.0092532713 | J153: JA | K153: https://finnhub.io/api/news?id=7d48082034dcd61f9df177502e82678bc76887a3a345bb490476a1d22c318f45
A154: 2026-07-03 | B154: SHW | C154: SHW | D154: 352.48001 | E154: 0.018581198 | F154: 0.039518771 | G154: 0.20300345 | H154: 0.093032539 | I154: 0.0092532713 | J154: JA | K154: https://finnhub.io/api/news?id=7d48082034dcd61f9df177502e82678bc76887a3a345bb490476a1d22c318f45
A155: 2026-07-03 | B155: ITW | C155: ITW | D155: 272.76001 | E155: 0.014090822 | F155: 0.01408645 | G155: 0.10391741 | H155: 0.12118235 | I155: 0.090480489 | J155: JA | K155: https://finnhub.io/api/news?id=bbdd4adc53276bfc9d40837011f07ffc4d24777b02544c64920cafcc1f39d6e6
A156: 2026-07-03 | B156: V | C156: V | D156: 362.13 | E156: 0.031474361 | F156: 0.095637229 | G156: 0.14121391 | H156: 0.036836821 | I156: 0.030405995 | J156: JA | K156: https://finnhub.io/api/news?id=14ad7625a72b8c399caab2e42a73c6b9bd876d9c9b3a46dabbc3bfc3a672fe36
A157: 2026-07-03 | B157: PM | C157: PM | D157: 182.27 | E157: 0.025775236 | F157: 0.018666583 | G157: 0.058281254 | H157: 0.15599582 | I157: 0.073680654 | J157: JA | K157: https://finnhub.io/api/news?id=840d41f2aa0e747f2602ed1773f4dbb206a469c2fa2c4c15ce0627a85dc8e190
A158: 2026-07-03 | B158: UPS | C158: UPS | D158: 110.66 | E158: 0.0102246 | F158: 0.012350253 | G158: 0.01588179 | H158: 0.15026321 | I158: 0.12061949 | J158: JA | K158: https://finnhub.io/api/news?id=bdfcb8dda79efd2da7e110be7fb6810cf6d812cc10e9bd26808c2821428343a0
... A163: 2026-07-03 | B163: PEP | C163: PEP | D163: 144.22 | E163: 0.021677511 | F163: 0.033686904 | G163: 0.026319381 | H163: 0.024521811 | I163: 0.098549452 | J163: JA | K163: https://finnhub.io/api/news?id=91a14ee5d1a6dab5b6ac083158480a7491177be30dd8eac1bb3bbc12c45d5a17
A164: 2026-07-03 | B164: BRK-B | C164: BRK-B | D164: 507.78 | E164: 0.016088383 | F164: 0.040938073 | G164: 0.076923052 | H164: 0.010205919 | I164: 0.056818155 | J164: JA
A165: 2026-07-06 | B165: AMD | C165: AMD | D165: 556.71997 | E165: 0.075122558 | F165: 0.031937535 | G165: 0.19370463 | H165: 1.4912515 | I165: 3.0368353 | J165: JA | K165: https://finnhub.io/api/news?id=e417f0bbb48196563d43efb3e0c4a5727402b839a8324a731be011c44b54bd6a
A166: 2026-07-06 | B166: MRNA | C166: MRNA | D166: 82.735001 | E166: 0.037299378 | F166: 0.18701584 | G166: 0.74399247 | H166: 1.6809786 | I166: 1.7135127 | J166: JA | K166: https://finnhub.io/api/news?id=e417f0bbb48196563d43efb3e0c4a5727402b839a8324a731be011c44b54bd6a
A167: 2026-07-06 | B167: VRT | C167: VRT | D167: 320.70999 | E167: 0.067148014 | F167: 0.044760042 | G167: 0.067441004 | H167: 0.82707742 | I167: 1.5114462 | J167: JA | K167: https://finnhub.io/api/news?id=e417f0bbb48196563d43efb3e0c4a5727402b839a8324a731be011c44b54bd6a
A168: 2026-07-06 | B168: GEV | C168: GEV | D168: 1151.645 | E168: 0.034619251 | F168: 0.044566498 | G168: 0.23417005 | H168: 0.69785751 | I168: 1.2334106 | J168: JA | K168: https://finnhub.io/api/news?id=4843b1c4e75158c240eeadc80dd5c21992e3f151f2a27e0ab7c7eff83cedd7e7
A169: 2026-07-06 | B169: PANW | C169: PANW | D169: 357.64001 | E169: 0.027524039 | F169: 0.07722896 | G169: 0.3146114 | H169: 0.99386756 | I169: 0.77207413 | J169: JA | K169: https://finnhub.io/api/news?id=b7099b8b7d455bebf0434085da53e18ca319e522fe2ecb9a9bc07f6979dc38a7
A170: 2026-07-06 | B170: FTNT | C170: FTNT | D170: 162.91 | E170: 0.042624023 | F170: 0.048192032 | G170: 0.12600229 | H170: 1.091808 | I170: 0.54183227 | J170: JA | K170: https://finnhub.io/api/news?id=e9b52115c6d8ac4db909cf7a1abbb47b9fd97fd79dd35a8dc2f1cf47f1de1a91
A171: 2026-07-06 | B171: OKTA | C171: OKTA | D171: 148.03999 | E171: 0.046810884 | F171: 0.12740839 | G171: 0.24696759 | H171: 0.76996646 | I171: 0.4936938 | J171: JA | K171: https://finnhub.io/api/news?id=b7099b8b7d455bebf0434085da53e18ca319e522fe2ecb9a9bc07f6979dc38a7
A172: 2026-07-06 | B172: ILMN | C172: ILMN | D172: 194.44501 | E172: 0.030554457 | F172: 0.073688574 | G172: 0.19791152 | H172: 0.44730181 | I172: 0.92901787 | J172: JA | K172: https://finnhub.io/api/news?id=658c271df34013dfee20233d3322197355cb5a16c8de8ba929ef9b3e1a2bcd8a
A173: 2026-07-06 | B173: VLO | C173: VLO | D173: 271.09509 | E173: 0.012455493 | F173: 0.017929879 | G173: 0.059710285 | H173: 0.6577882 | I173: 0.92302754 | J173: JA | K173: https://finnhub.io/api/news?id=fbba858a3a697de2358391b8e79f76ca2ae4f7e7eacd5848241de13919d016fe
A174: 2026-07-06 | B174: CRWD | C174: CRWD | D174: 201.17999 | E174: 0.037117214 | F174: 0.083199849 | G174: 0.19924883 | H174: 0.77415229 | I174: 0.5652986 | J174: JA | K174: https://finnhub.io/api/news?id=b7099b8b7d455bebf0434085da53e18ca319e522fe2ecb9a9bc07f6979dc38a7
A175: 2026-07-06 | B175: TSM | C175: TSM | D175: 455.95001 | E175: 0.05018889 | F175: 0.0018677348 | G175: 0.10079671 | H175: 0.43395259 | I175: 0.96334145 | J175: JA | K175: https://finnhub.io/api/news?id=c494e6706a91a668506399ca12b49420621b79eb5643ca92784eab5302ef49cd
A176: 2026-07-06 | B176: TXN | C176: TXN | D176: 304.10001 | E176: 0.037600723 | F176: 0.065223464 | G176: 0.066792986 | H176: 0.73298883 | I176: 0.4472251 | J176: JA | K176: https://finnhub.io/api/news?id=55d40c15eb4eb3414dd3ca1218da950f595e78046453acd7c52938dc1ea6a147
... A226: 2026-07-07 | B226: CB | C226: CB | D226: 362.6001 | E226: 0.017025493 | F226: 0.064154804 | G226: 0.11481737 | H226: 0.15741355 | I226: 0.30301524 | J226: JA | K226: https://finnhub.io/api/news?id=105e9daab0c2bd7d8ef2cbabc00e1a53c7203e51239ddad22d4c210fa5708a54
A227: 2026-07-07 | B227: EAT | C227: EAT | D227: 180.81 | E227: 0.025697747 | F227: 0.076249985 | G227: 0.28727032 | H227: 0.20959327 | I227: 0.042613306 | J227: JA
A228: 2026-07-07 | B228: D | C228: D | D228: 70.125 | E228: 0.01248914 | F228: 0.026870685 | G228: 0.048206254 | H228: 0.21966232 | I228: 0.29734344 | J228: JA | K228: https://finnhub.io/api/news?id=3837ee6682f5a781de25cafd56188a7999d60d02d5b9e5edc0a53d1635a99823
A229: 2026-07-07 | B229: AMGN | C229: AMGN | D229: 372.48499 | E229: 0.016496515 | F229: 0.028623082 | G229: 0.065521482 | H229: 0.17828102 | I229: 0.30971531 | J229: JA | K229: https://finnhub.io/api/news?id=736265c3bcf026a1c9eaf58c5f2d746749e1e592e9b0699d74bef818c0ec74df
A230: 2026-07-07 | B230: UNP | C230: UNP | D230: 284.51999 | E230: 0.0068296567 | F230: 0.046029371 | G230: 0.044800167 | H230: 0.23935329 | I230: 0.23637346 | J230: JA | K230: https://finnhub.io/api/news?id=3ccb678dc772a7a3a2ea819a993761b7c130f5ced85c37d597f535aa75842b7f
A231: 2026-07-07 | B231: GILD | C231: GILD | D231: 135.36501 | E231: 0.044402476 | F231: 0.0714343 | G231: 0.054929012 | H231: 0.15831312 | I231: 0.24254203 | J231: JA | K231: https://finnhub.io/api/news?id=6b219e38084e6475784ec645d74c2fa22bed3720375dabbf7ff1d4559a279cdd
A232: 2026-07-07 | B232: BAC | C232: BAC | D232: 60.634998 | E232: 0.012270397 | F232: 0.064145293 | G232: 0.12641643 | H232: 0.077423156 | I232: 0.27323966 | J232: JA | K232: https://finnhub.io/api/news?id=117e6e771dada702f24697ee912a8ceb5d561106c2bac50946a4f69ef689d973
A233: 2026-07-07 | B233: PSA | C233: PSA | D233: 327.315 | E233: 0.010231489 | F233: 0.028290047 | G233: 0.066764576 | H233: 0.27910456 | I233: 0.16765898 | J233: JA | K233: https://finnhub.io/api/news?id=930d656d66c20e68b1eb54474c83d19daf0694724e1704bb797e426eae4c782e
A234: 2026-07-07 | B234: LIN | C234: LIN | D234: 543.16998 | E234: 0.0049026184 | F234: 0.046691294 | G234: 0.069442783 | H234: 0.25835709 | I234: 0.1685648 | J234: JA | K234: https://finnhub.io/api/news?id=0236820e6a32ab4066a97c1182a2d1698b6f171243ae18b7bb6b25d73147e6d8
A235: 2026-07-07 | B235: GD | C235: GD | D235: 377.17499 | E235: 0.00078269716 | F235: 0.069430286 | G235: 0.093508168 | H235: 0.074781748 | I235: 0.30266102 | J235: JA | K235: https://finnhub.io/api/news?id=9fa749ae2a08ff47d7fdfcb2bfaad3dc7a5e73f1fe7521b5db52bc83ccbcd812
...
